rtdl/__init__.py
rtdl/data.py
rtdl/functional.py
rtdl/modules.py
rtdl/tests/__init__.py
rtdl/tests/test_data.py
rtdl/tests/test_modules.py
rtdl/tests/test_vs_paper.py
rtdl-0.0.13.dist-info/LICENSE
rtdl-0.0.13.dist-info/WHEEL
rtdl-0.0.13.dist-info/METADATA
rtdl-0.0.13.dist-info/RECORD
